webbits/__init__.py
webbits/html/__init__.py
webbits/html/_constants.py
webbits/html/_elements.py
webbits/html/_h.py
webbits/lib.py
webbits-0.1.4.dist-info/AUTHORS.rst
webbits-0.1.4.dist-info/LICENSE
webbits-0.1.4.dist-info/METADATA
webbits-0.1.4.dist-info/WHEEL
webbits-0.1.4.dist-info/RECORD
