Metadata-Version: 2.1
Name: webbits
Version: 0.1.4
Summary: Top-level package for Webbits.
Home-page: https://github.com/sfermigier/webbits
Author: Abilian SAS
Author-email: sf@abilian.com
Requires-Python: >=3.10,<4.0
Classifier: Development Status :: 2 - Pre-Alpha
Classifier: Intended Audience :: Developers
Classifier: Natural Language :: English
Classifier: Programming Language :: Python :: 3
Classifier: Programming Language :: Python :: 3.10
Classifier: Programming Language :: Python :: 3.11
Classifier: Programming Language :: Python :: 3.12
Classifier: Programming Language :: Python :: 3.8
Classifier: Programming Language :: Python :: 3.9
Requires-Dist: defusedxml (>=0.7.1)
Requires-Dist: markupsafe (>=2)
